sonarleaks/__init__.py
sonarleaks/__main__.py
sonarleaks-1.0.0.dist-info/LICENSE
sonarleaks-1.0.0.dist-info/METADATA
sonarleaks-1.0.0.dist-info/WHEEL
sonarleaks-1.0.0.dist-info/entry_points.txt
sonarleaks-1.0.0.dist-info/top_level.txt
sonarleaks-1.0.0.dist-info/RECORD
