Metadata-Version: 2.1
Name: sonarleaks
Version: 1.0.0
Summary: Sonarleaks
Home-page: https://github.com/cosad3s/sonarleaks
Author: Sébastien Copin
Author-email: cosad3s@outlook.com
License: GPL-3.0 License
Keywords: leaks,sonarcloud,osint,bugbounty
Classifier: Topic :: Internet :: WWW/HTTP :: Indexing/Search
Classifier: Topic :: Security
Classifier: Programming Language :: Python :: 3
License-File: LICENSE
Requires-Dist: requests
Requires-Dist: argparse
